kft/__init__.py
kft/kft.py
kft/test_kft.py
kfulltree-0.0.1.dist-info/METADATA
kfulltree-0.0.1.dist-info/WHEEL
kfulltree-0.0.1.dist-info/entry_points.txt
kfulltree-0.0.1.dist-info/licenses/LICENSE
kfulltree-0.0.1.dist-info/RECORD
