Metadata-Version: 2.4
Name: kfulltree
Version: 0.0.1
Summary: Python implementation of the k-Full Tree (kFT) algorithm for geo-referenced time-series data summarization
Project-URL: Homepage, https://github.com/yourusername/kfulltree
Project-URL: Repository, https://github.com/yourusername/kfulltree.git
Project-URL: Issues, https://github.com/yourusername/kfulltree/issues
Author-email: Your Name <your.email@example.com>
License: MIT
License-File: LICENSE
Keywords: clustering,data-mining,graph-analysis,spatio-temporal,time-series
Classifier: Development Status :: 4 - Beta
Classifier: Intended Audience :: Science/Research
Classifier: License :: OSI Approved :: MIT License
Classifier: Programming Language :: Python :: 3
Classifier: Programming Language :: Python :: 3.13
Classifier: Topic :: Scientific/Engineering :: Information Analysis
Requires-Python: >=3.13
Requires-Dist: networkx>=3.5
Requires-Dist: numpy>=2.3.2
